bluejay/__init__.py
bluejay/client.py
bluejay/event.py
bluejay/interface.py
bluejay/backend/__init__.py
bluejay/backend/command.py
bluejay/backend/encode.py
bluejay/backend/interface.py
bluejay/backend/logging.py
bluejay/backend/sns.py
fundingoptions_bluejay-0.3.0.dist-info/LICENSE
fundingoptions_bluejay-0.3.0.dist-info/WHEEL
fundingoptions_bluejay-0.3.0.dist-info/METADATA
fundingoptions_bluejay-0.3.0.dist-info/RECORD
