Metadata-Version: 2.1
Name: fundingoptions-bluejay
Version: 0.3.0
Summary: The BlueJay Client
Home-page: https://github.com/FundingOptions/bluejay-client
Author: Funding Options
Author-email: techsupport@fundingoptions.com
Requires-Python: >=3.5
Classifier: License :: OSI Approved :: MIT License
Requires-Dist: attrs
Requires-Dist: typing_extensions
Requires-Dist: black ; extra == "dev"
Requires-Dist: isort ; extra == "dev"
Requires-Dist: autoflake ; extra == "dev"
Requires-Dist: mypy ; extra == "dev"
Requires-Dist: tox ; extra == "dev"
Requires-Dist: boto3 ; extra == "sns"
Requires-Dist: faker ; extra == "test"
Requires-Dist: pytest ; extra == "test"
Requires-Dist: pytest-cov ; extra == "test"
Requires-Dist: pytest-randomly ; extra == "test"
Provides-Extra: dev
Provides-Extra: sns
Provides-Extra: test
